{"version":"3","listProblem":[{
  "tool": "Code Inspection",
  "category": "Code style issues",
  "type": "C-style array declaration",
  "severity": "High",
  "comment": "C-style array declaration of parameter 'args'",
  "detailsInfo": "Reports array declarations written in C-style syntax in which the array indicator brackets are placed after the variable name or after the method parameter list.\n\nExample:\n\n\n      public String process(String value[])[] {\n        return value;\n      }\n\nMost code styles prefer Java-style array declarations in which the array indicator brackets are attached to the type name, for example:\n\n\n      public String[] process(String[] value) {\n        return value;\n      }\n\nConfigure the inspection:\n\n\nUse the **Ignore C-style declarations in variables** option to report C-style array declaration of method return types only.",
  "sources": [
    {
      "type": "file",
      "path": "src/main/java/it/francescopessina/esselunga/Main.java",
      "language": "JAVA",
      "line": 50,
      "offset": 34,
      "length": 4,
      "code": {
        "startLine": 48,
        "length": 4,
        "offset": 90,
        "surroundingCode": "  private static final int MAX_WAIT_TIME_SECONDS = 300;\n\n  public static void main(String args[]) {\n    readProperties();\n    driver = new ChromeDriver();"
      }
    }
  ],
  "attributes": {
    "module": "SeleniumEsselungaMaven",
    "inspectionName": "CStyleArrayDeclaration"
  },
  "hash": "890ce5e672351d12e446249d80095693885ac779fece0baf52d4750a14f28a98"
}]}